Metadata-Version: 2.1
Name: cos-utils
Version: 0.0.12
Summary: Cloud Object Storage utility
Home-page: https://github.com/CODAIT/cos-utils
Author: Patrick Titzler
Author-email: ptitzler@us.ibm.com
License: Apache-2.0
Keywords: Cloud Object Storage,upload,download,list
Platform: UNKNOWN
Classifier: Development Status :: 4 - Beta
Classifier: License :: OSI Approved :: Apache Software License
Classifier: Programming Language :: Python :: 3.6
Classifier: Programming Language :: Python :: 3.7
